pelican/plugins/youtube/__init__.py
pelican/plugins/youtube/youtube.css
pelican/plugins/youtube/youtube.py
pelican_youtube-0.3.0.dist-info/METADATA
pelican_youtube-0.3.0.dist-info/WHEEL
pelican_youtube-0.3.0.dist-info/entry_points.txt
pelican_youtube-0.3.0.dist-info/licenses/LICENSE
pelican_youtube-0.3.0.dist-info/RECORD
