Metadata-Version: 2.4
Name: pelican-youtube
Version: 0.3.0
Summary: Easily embed YouTube videos in your posts
Author-Email: Kura <kura@kura.gg>, Peter Bittner <django@gittner.it>
Maintainer-Email: Kura <kura@kura.gg>
License-Expression: MIT
License-File: LICENSE
Classifier: Development Status :: 5 - Production/Stable
Classifier: Intended Audience :: Developers
Classifier: Operating System :: OS Independent
Classifier: Programming Language :: Python :: 3
Classifier: Programming Language :: Python :: 3.8
Classifier: Programming Language :: Python :: 3.9
Classifier: Programming Language :: Python :: 3.10
Classifier: Programming Language :: Python :: 3.11
Classifier: Programming Language :: Python :: 3.12
Classifier: Programming Language :: Python :: 3.13
Classifier: Programming Language :: Python :: Implementation :: CPython
Classifier: Programming Language :: Python
Classifier: Topic :: Internet :: WWW/HTTP
Classifier: Topic :: Software Development :: Libraries :: Python Modules
Classifier: Topic :: Text Processing
Project-URL: Homepage, https://github.com/kura/pelican_youtube
Requires-Python: <4.0,>=3.8
Requires-Dist: pelican>=4.5
